paint.py
term_paint-1.0.2.dist-info/METADATA
term_paint-1.0.2.dist-info/WHEEL
term_paint-1.0.2.dist-info/entry_points.txt
term_paint-1.0.2.dist-info/top_level.txt
term_paint-1.0.2.dist-info/RECORD
