Metadata-Version: 2.4
Name: term-paint
Version: 1.0.2
Summary: CLI tool for drawing pixel art in the terminal with keyboard (WASD) controls.
Requires-Python: >=3.9
Requires-Dist: argparse>=1.4.0
Requires-Dist: pillow>=11.3.0
Requires-Dist: windows-curses>=2.4.1; sys_platform == "win32"
